toradh/__init__.py
toradh/option.py
toradh/py.typed
toradh/result.py
toradh-0.3.0.dist-info/LICENSE
toradh-0.3.0.dist-info/METADATA
toradh-0.3.0.dist-info/WHEEL
toradh-0.3.0.dist-info/RECORD
