Metadata-Version: 2.3
Name: toradh
Version: 0.3.0
Summary: Minimalistic library intended to bring better flow control to Python.
License: MIT
Keywords: toradh,rust,result,optional,control-flow
Author: Santiago Bassani
Author-email: santiago.bassani96@gmail.com
Requires-Python: >=3.9,<4.0
Classifier: License :: OSI Approved :: MIT License
Classifier: Programming Language :: Python :: 3
Classifier: Programming Language :: Python :: 3.9
Classifier: Programming Language :: Python :: 3.10
Classifier: Programming Language :: Python :: 3.11
Classifier: Programming Language :: Python :: 3.12
Classifier: Programming Language :: Python :: 3.13
Requires-Dist: pydantic (>=2.11.7,<3.0.0)
Requires-Dist: typeguard (>=4.3.0,<5.0.0)
Project-URL: Homepage, https://github.com/levensworth/toradh
Project-URL: Repository, https://github.com/levensworth/toradh
